{
    "quotes": [
        {
            "text": "Nammadha pooley",
            "author": "Deva"
          },

      {
        "text": "Excuses don't burn calories.",
        "author": "Unknown"
      },
      {
        "text": "Stop waiting for things to happen. Go out and make them happen.",
        "author": "Unknown"
      },
      {
        "text": "Pain is temporary. Quitting lasts forever.",
        "author": "Lance Armstrong"
      },
      {
        "text": "The only way to achieve the impossible is to believe it is possible.",
        "author": "Charles Kingsleigh"
      },
      {
        "text": "Don't be afraid to give up the good to go for the great.",
        "author": "John D. Rockefeller"
      },
      {
        "text": "Success is not for the lazy.",
        "author": "Unknown"
      }
    ]
  }
  